dredge/__init__.py
dredge/__main__.py
dredge/batch_pipeline.py
dredge/cache.py
dredge/cli.py
dredge/config.py
dredge/health.py
dredge/mcp_server.py
dredge/monitoring.py
dredge/server.py
dredge/string_theory.py
dredge/workers.py
dredge/custom_ops/__init__.py
dredge/custom_ops/build.py
dredge_cli-0.1.5.dist-info/licenses/AUTHORS.md
dredge_cli-0.1.5.dist-info/licenses/LICENSE
dredge_cli-0.1.5.dist-info/METADATA
dredge_cli-0.1.5.dist-info/WHEEL
dredge_cli-0.1.5.dist-info/entry_points.txt
dredge_cli-0.1.5.dist-info/top_level.txt
dredge_cli-0.1.5.dist-info/RECORD
