Metadata-Version: 2.4
Name: dredge-cli
Version: 0.1.5
Summary: DREDGE — A small Python utility (scaffold).
Author: QueenFi703
License: MIT
Project-URL: Homepage, https://github.com/QueenFi703/DREDGE
Classifier: Programming Language :: Python :: 3
Classifier: Programming Language :: Python :: 3 :: Only
Classifier: License :: OSI Approved :: MIT License
Classifier: Operating System :: OS Independent
Requires-Python: <3.15,>=3.9
License-File: LICENSE
License-File: AUTHORS.md
Dynamic: license-file
